aalgorithm/__init__.py
aalgorithm/cli.py
aalgorithm/content.py
aalgorithm/llm.py
aalgorithm/search.py
aalgorithm/utils.py
aalgorithm/agents/__init__.py
aalgorithm/agents/deepresearch.py
aalgorithm/agents/deepsearch.py
aalgorithm/agents/autoapi/README_PORTABLE_API.md
aalgorithm/agents/autoapi/__init__.py
aalgorithm/agents/autoapi/agent.py
aalgorithm/agents/autoapi/api.py
aalgorithm/agents/autoapi/config_manager.py
aalgorithm/agents/autoapi/dynamic_router.py
aalgorithm/agents/autoapi/environment_manager.py
aalgorithm/agents/autoapi/manager.py
aalgorithm/agents/autoapi/path_resolver.py
aalgorithm/agents/autoapi/prompts.py
aalgorithm/agents/autoapi/script_analyzer.py
aalgorithm/agents/autoapi/script_generator.py
aalgorithm/agents/autoapi/script_repository.py
aalgorithm/agents/autoapi/script_tester.py
aalgorithm/agents/autodeploy/__init__.py
aalgorithm/agents/autodeploy/command.py
aalgorithm/agents/autodeploy/controller.py
aalgorithm/agents/autodeploy/entry.py
aalgorithm/agents/autodeploy/git_operations.py
aalgorithm/agents/autodeploy/graph.py
aalgorithm/agents/autodeploy/log_config.py
aalgorithm/agents/autodeploy/nodes.py
aalgorithm/agents/autodeploy/prompts.py
aalgorithm/agents/autodeploy/react_search.py
aalgorithm-0.1.5.dist-info/METADATA
aalgorithm-0.1.5.dist-info/WHEEL
aalgorithm-0.1.5.dist-info/entry_points.txt
aalgorithm-0.1.5.dist-info/RECORD
