Metadata-Version: 2.4
Name: aalgorithm
Version: 0.1.5
Summary: Add your description here
Author-email: jarlor <jarlorzhang@outlook.com>
Requires-Python: >=3.12
Requires-Dist: diskcache>=5.6.3
Requires-Dist: json-repair>=0.46.2
Requires-Dist: langchain-core>=0.1.0
Requires-Dist: loguru
Requires-Dist: openai
Requires-Dist: python-dotenv>=1.1.0
Requires-Dist: requests
Requires-Dist: trafilatura>=2.0.0
Provides-Extra: autoapi
Requires-Dist: fastapi>=0.116.0; extra == 'autoapi'
Requires-Dist: uvicorn>=0.34.3; extra == 'autoapi'
Provides-Extra: autodeploy
Requires-Dist: fastapi>=0.116.0; extra == 'autodeploy'
Requires-Dist: fastmcp>=2.9.0; extra == 'autodeploy'
Requires-Dist: neo4j>=5.28.1; extra == 'autodeploy'
Requires-Dist: psutil>=7.0.0; extra == 'autodeploy'
